curl_proxies_checker
