Metadata-Version: 1.1
Name: curl-proxies-checker
Version: 0.0.6
Summary: Lib for check proxies
Home-page: https://github.com/lispython/curl-proxies-checker
Author: Alex
Author-email: alex@obout.ru
License: BSD
Platform: UNKNOWN
Classifier: Environment :: Web Environment
Classifier: License :: OSI Approved :: BSD License
Classifier: Programming Language :: Python
